MANIFEST.in
setup.py
pure_pcapy/__init__.py
pure_pcapy3.egg-info/PKG-INFO
pure_pcapy3.egg-info/SOURCES.txt
pure_pcapy3.egg-info/dependency_links.txt
pure_pcapy3.egg-info/requires.txt
pure_pcapy3.egg-info/top_level.txt
test/__init__.py