Metadata-Version: 1.0
Name: pure-pcapy3
Version: 1.0.1
Summary: Pure Python reimplementation of pcapy. This package is API compatible and a drop-in replacement.
Home-page: http://bitbucket.org/viraptor/pure-pcapy/overview
Author: Stanislaw Pitucha
Author-email: viraptor@gmail.com
License: Simplified BSD
Keywords: pcap,file,reader,writer
Platform: UNKNOWN
